{
    "180": {
        "buses": [
            "Not Applicable"
        ], 
        "certified": "False", 
        "class_names": [
            "NemSyringeAxis"
        ], 
        "detail_url": "http://www.tango-controls.org/developers/dsc/ds/180/", 
        "development_status": "released", 
        "documentation": [
            {
                "documentation_type": "Generated", 
                "pk": 329, 
                "title": "PDF generated from POGO", 
                "updated_by_script": true, 
                "url": "http://www.esrf.eu/computing/cs/tango/tango_doc/ds_doc/tango-ds/Motion/NemSyringeAxis/NemSyringeAxis.pdf"
            }
        ], 
        "families": [
            "Motion"
        ], 
        "last_update": "2017-02-23 10:40:14.223139+00:00", 
        "last_update_method": "url", 
        "license": "None", 
        "manufacturers": [
            "none"
        ], 
        "name": "NemSyringeAxis", 
        "products": [
            ""
        ], 
        "repository_contact_email": "", 
        "repository_url": "http://svn.code.sf.net/p/tango-ds/code/DeviceClasses/Motion/MotorControllers/NemSyringeAxis", 
        "status": "updated", 
        "tag": "Release_1_2", 
        "update_url": "http://www.tango-controls.org/developers/dsc/ds/180/update/", 
        "updated_by_script": true
    }
}