{
    "2206": {
        "buses": [
            "Socket"
        ], 
        "certified": "False", 
        "class_names": [
            "C400Pyramid"
        ], 
        "detail_url": "https://www.tango-controls.org/developers/dsc/ds/2206/", 
        "development_status": "released", 
        "documentation": [], 
        "families": [
            "CounterTimer"
        ], 
        "last_update": "2020-02-08 03:23:52.620211+00:00", 
        "last_update_method": "url", 
        "license": "GPL", 
        "manufacturers": [
            "Pyramid Technical Consultants"
        ], 
        "name": "C400Pyramid", 
        "products": [
            "C400"
        ], 
        "repository_contact_email": "", 
        "repository_url": "http://svn.code.sf.net/p/tango-ds/code/DeviceClasses/CounterTimer/C400Pyramid", 
        "status": "updated", 
        "tag": "Release_1_0", 
        "update_url": "https://www.tango-controls.org/developers/dsc/ds/2206/update/", 
        "updated_by_script": true
    }
}