{
    "1144": {
        "buses": [
            "Socket"
        ], 
        "certified": "False", 
        "class_names": [
            "GEpressCtrlPACE5000"
        ], 
        "detail_url": "http://www.tango-controls.org/developers/dsc/ds/1144/", 
        "development_status": "released", 
        "documentation": [
            {
                "documentation_type": "Generated", 
                "pk": 264, 
                "title": "PDF generated from POGO", 
                "updated_by_script": true, 
                "url": "http://www.esrf.eu/computing/cs/tango/tango_doc/ds_doc/tango-ds/MeasureInstruments/GEpressCtrlPACE5000/GEpressCtrlPACE5000.pdf"
            }
        ], 
        "families": [
            "MeasureInstruments"
        ], 
        "last_update": "2019-02-02 03:34:29.331975+00:00", 
        "last_update_method": "url", 
        "license": "GPL", 
        "manufacturers": [
            "GE"
        ], 
        "name": "GEpressCtrlPACE5000", 
        "products": [
            "PACE-5000"
        ], 
        "repository_contact_email": "", 
        "repository_url": "http://svn.code.sf.net/p/tango-ds/code/DeviceClasses/MeasureInstruments/GEpressCtrlPACE5000", 
        "status": "updated", 
        "tag": "Release_1_0", 
        "update_url": "http://www.tango-controls.org/developers/dsc/ds/1144/update/", 
        "updated_by_script": true
    }
}