{
    "936": {
        "buses": [
            "rr"
        ], 
        "certified": "False", 
        "class_names": [
            "Falcon"
        ], 
        "detail_url": "http://www.tango-controls.org/developers/dsc/ds/936/", 
        "development_status": "new", 
        "documentation": [], 
        "families": [
            "Acquisition"
        ], 
        "last_update": "2018-02-22 14:44:39.661815+00:00", 
        "last_update_method": "file", 
        "license": "None", 
        "manufacturers": [
            "none"
        ], 
        "name": "falcon", 
        "products": [
            ""
        ], 
        "repository_contact_email": "", 
        "repository_url": "http://svn.code.sf.net/p/tango-ds/code/DeviceClasses/Acquisition/2D/falcon", 
        "status": "updated", 
        "tag": "", 
        "update_url": "http://www.tango-controls.org/developers/dsc/ds/936/update/", 
        "updated_by_script": true
    }
}