{
    "406": {
        "buses": [
            "Serial Line"
        ], 
        "certified": "False", 
        "class_names": [
            "VarianDualIP"
        ], 
        "detail_url": "http://www.tango-controls.org/developers/dsc/ds/406/", 
        "development_status": "released", 
        "documentation": [
            {
                "documentation_type": "Generated", 
                "pk": 568, 
                "title": "PDF generated from POGO", 
                "updated_by_script": true, 
                "url": "http://www.esrf.eu/computing/cs/tango/tango_doc/ds_doc/tango-ds/Vacuum/VarianDualIP/VarianDualIP.pdf"
            }
        ], 
        "families": [
            "Vacuum"
        ], 
        "last_update": "2017-02-23 11:50:49.500308+00:00", 
        "last_update_method": "url", 
        "license": "GPL", 
        "manufacturers": [
            "Varian"
        ], 
        "name": "VarianDualIP", 
        "products": [
            "Dual IP"
        ], 
        "repository_contact_email": "", 
        "repository_url": "http://svn.code.sf.net/p/tango-ds/code/DeviceClasses/Vacuum/VarianDualIP", 
        "status": "updated", 
        "tag": "VarianDualIP-Release-2.4", 
        "update_url": "http://www.tango-controls.org/developers/dsc/ds/406/update/", 
        "updated_by_script": true
    }
}