{
    "1420": {
        "buses": [
            ""
        ], 
        "certified": "False", 
        "class_names": [
            "Encoder"
        ], 
        "detail_url": "http://www.tango-controls.org/developers/dsc/ds/1420/", 
        "development_status": "released", 
        "documentation": [
            {
                "documentation_type": "Generated", 
                "pk": 497, 
                "title": "PDF generated from POGO", 
                "updated_by_script": true, 
                "url": "http://www.esrf.eu/computing/cs/tango/tango_doc/ds_doc/tango-ds/StandardInterfaces/Encoder/Encoder.pdf"
            }
        ], 
        "families": [
            "StandardInterfaces"
        ], 
        "last_update": "2017-04-20 13:17:56.599455+00:00", 
        "last_update_method": "file", 
        "license": "None", 
        "manufacturers": [
            ""
        ], 
        "name": "Encoder", 
        "products": [
            ""
        ], 
        "repository_contact_email": "", 
        "repository_url": "http://svn.code.sf.net/p/tango-ds/code/DeviceClasses/StandardInterfaces/Encoder", 
        "status": "updated", 
        "tag": "Release_1_0", 
        "update_url": "http://www.tango-controls.org/developers/dsc/ds/1420/update/", 
        "updated_by_script": true
    }
}